pg/pg.py
postgres_helper-0.0.5.dist-info/LICENSE
postgres_helper-0.0.5.dist-info/METADATA
postgres_helper-0.0.5.dist-info/WHEEL
postgres_helper-0.0.5.dist-info/top_level.txt
postgres_helper-0.0.5.dist-info/RECORD
