Metadata-Version: 2.1
Name: postgres-helper
Version: 0.0.5
Summary: Package for Postgres query on python
Home-page: https://github.com/iamtekson/postgres-helper
Author: Tek Kshetri
Author-email: iamtekson@gmail.com
License: UNKNOWN
Keywords: postgresql,postgres,database,sql,api,table,pg,postGIS
Platform: UNKNOWN
Classifier: Programming Language :: Python :: 3
Classifier: License :: OSI Approved :: MIT License
Classifier: Operating System :: OS Independent
Requires-Python: >=3.6
License-File: LICENSE
